sqlacodegen/__init__.py
sqlacodegen/codegen.py
sqlacodegen/main.py
sukiyou_sql-1.4.1.dist-info/LICENSE
sukiyou_sql-1.4.1.dist-info/METADATA
sukiyou_sql-1.4.1.dist-info/WHEEL
sukiyou_sql-1.4.1.dist-info/top_level.txt
sukiyou_sql-1.4.1.dist-info/RECORD
