Metadata-Version: 2.1
Name: sukiyou-sql
Version: 1.4.1
Summary: 自用-生成orm类
Home-page: UNKNOWN
Author: sukiyou
Author-email: s844562300@163.com
License: UNKNOWN
Platform: UNKNOWN
Classifier: Programming Language :: Python :: 3
Classifier: License :: OSI Approved :: MIT License
Classifier: Operating System :: OS Independent
Requires-Python: >=3.6
Requires-Dist: sqlacodegen
